[
  {
    "BPM": 140,
    "TITLE": "Get on the Floor",
    "ARTIST": "Audition",
    "MP3": ""
  },
  {
    "BPM": 140,
    "TITLE": "DJ Euro Mix",
    "ARTIST": "Audition",
    "MP3": ""
  },
  {
    "BPM": 140,
    "TITLE": "Doo Doop",
    "ARTIST": "Audition",
    "MP3": ""
  },
  {
    "BPM": 140,
    "TITLE": "Driving At Night",
    "ARTIST": "Audition",
    "MP3": ""
  },
  {
    "BPM": 140,
    "TITLE": "I will be very good to you",
    "ARTIST": "Audition",
    "MP3": ""
  },
  {
    "BPM": 140,
    "TITLE": "I want to see you",
    "ARTIST": "Audition",
    "MP3": ""
  },
  {
    "BPM": 140,
    "TITLE": "Move",
    "ARTIST": "Audition",
    "MP3": ""
  },
  {
    "BPM": 140,
    "TITLE": "Pretty",
    "ARTIST": "Audition",
    "MP3": ""
  },
  {
    "BPM": 140,
    "TITLE": "Don't cry, my heart",
    "ARTIST": "Audition",
    "MP3": ""
  },
  {
    "BPM": 140,
    "TITLE": "Dancing Queen",
    "ARTIST": "Audition",
    "MP3": ""
  },
  {
    "BPM": 142,
    "TITLE": "Spain Moonlight",
    "ARTIST": "Audition",
    "MP3": ""
  },
  {
    "BPM": 142,
    "TITLE": "3254 Techno Party",
    "ARTIST": "Audition",
    "MP3": ""
  },
  {
    "BPM": 144,
    "TITLE": "At the same time",
    "ARTIST": "Audition",
    "MP3": ""
  },
  {
    "BPM": 145,
    "TITLE": "Heavy Metal Syndrome",
    "ARTIST": "Audition",
    "MP3": ""
  },
  {
    "BPM": 145,
    "TITLE": "Can't Let You Go",
    "ARTIST": "Audition",
    "MP3": ""
  },
  {
    "BPM": 148,
    "TITLE": "Pretend Ignorance",
    "ARTIST": "Audition",
    "MP3": ""
  },
  {
    "BPM": 150,
    "TITLE": "Go Go",
    "ARTIST": "Audition",
    "MP3": ""
  },
  {
    "BPM": 150,
    "TITLE": "You're Already Gone",
    "ARTIST": "Audition",
    "MP3": ""
  },
  {
    "BPM": 150,
    "TITLE": "Sorry",
    "ARTIST": "Audition",
    "MP3": ""
  },
  {
    "BPM": 150,
    "TITLE": "Like a fool",
    "ARTIST": "Audition",
    "MP3": ""
  },
  {
    "BPM": 150,
    "TITLE": "Come on",
    "ARTIST": "Audition",
    "MP3": ""
  },
  {
    "BPM": 164,
    "TITLE": "Train Running on The Sea When It Rains",
    "ARTIST": "Audition",
    "MP3": ""
  },
  {
    "BPM": 168,
    "TITLE": "Audition",
    "ARTIST": "Audition",
    "MP3": ""
  },
  {
    "BPM": 174,
    "TITLE": "Deck The Halls (HARD)",
    "ARTIST": "Audition",
    "MP3": ""
  },
  {
    "BPM": 175,
    "TITLE": "Everyday",
    "ARTIST": "Audition",
    "MP3": ""
  },
  {
    "BPM": 176,
    "TITLE": "still young",
    "ARTIST": "Audition",
    "MP3": ""
  },
  {
    "BPM": 190,
    "TITLE": "Fly High (Hard)",
    "ARTIST": "Audition",
    "MP3": ""
  },
  {
    "BPM": 185,
    "TITLE": "magic world",
    "ARTIST": "Audition",
    "MP3": ""
  }
]